nsec3_hash/__init__.py
nsec3_hash/cli.py
py_nsec3hash-1.0.2.dist-info/METADATA
py_nsec3hash-1.0.2.dist-info/WHEEL
py_nsec3hash-1.0.2.dist-info/entry_points.txt
py_nsec3hash-1.0.2.dist-info/licenses/LICENSE.TXT
py_nsec3hash-1.0.2.dist-info/RECORD
