Metadata-Version: 2.4
Name: py_nsec3hash
Version: 1.0.2
Summary: A tool to compute NSEC3 hashes for DNS labels
Project-URL: Repository, https://github.com/davidgroves/py_nsec3hash
Author: David Groves
License: Copyright 2025, David Groves
License-File: LICENSE.TXT
Classifier: Development Status :: 4 - Beta
Classifier: Intended Audience :: Developers
Classifier: License :: OSI Approved :: MIT License
Classifier: Programming Language :: Python :: 3
Classifier: Topic :: Internet :: Name Service (DNS)
Requires-Python: >=3.6
